{
  "file": "images/2e1df88f-dbe7-4cd0-b059-154b182db252___asbestos%20paper%20insulation_OIP.Ymqxg4AEAqfNWLNX32bUZgHaFj.jpg",
  "image_size": [
    {
      "width": 474,
      "height": 355,
      "depth": 3
    }
  ],
  "annotations": [
    {
      "class_id": 2,
      "left": 316,
      "width": 145,
      "top": 173,
      "height": 118
    },
    {
      "class_id": 2,
      "left": 27,
      "width": 198,
      "top": 235,
      "height": 102
    }
  ],
  "categories": [
    {
      "class_id": 0,
      "name": "termite_tubes"
    },
    {
      "class_id": 1,
      "name": "hot_water_expansion_tank"
    },
    {
      "class_id": 2,
      "name": "asbestos"
    },
    {
      "class_id": 3,
      "name": "pedestal_sump_pump"
    },
    {
      "class_id": 4,
      "name": "fuel_tank"
    },
    {
      "class_id": 5,
      "name": "water_softener"
    },
    {
      "class_id": 6,
      "name": "breaker_box"
    },
    {
      "class_id": 7,
      "name": "fire_damage"
    },
    {
      "class_id": 8,
      "name": "washer"
    },
    {
      "class_id": 9,
      "name": "dryer"
    },
    {
      "class_id": 10,
      "name": "smoke_detector"
    },
    {
      "class_id": 11,
      "name": "furnace"
    }
  ]
}