{
  "file": "images/c1951949-c4b7-45b7-998b-596765b0f51c___termite%20tubes_OIP.hVeyfKHutqeDH2Qabfe6ngAAAA.jpg",
  "image_size": [
    {
      "width": 225,
      "height": 300,
      "depth": 3
    }
  ],
  "annotations": [
    {
      "class_id": 0,
      "left": 161,
      "width": 47,
      "top": 61,
      "height": 82
    },
    {
      "class_id": 0,
      "left": 23,
      "width": 84,
      "top": 57,
      "height": 148
    }
  ],
  "categories": [
    {
      "class_id": 0,
      "name": "termite_tubes"
    },
    {
      "class_id": 1,
      "name": "hot_water_expansion_tank"
    },
    {
      "class_id": 2,
      "name": "asbestos"
    },
    {
      "class_id": 3,
      "name": "pedestal_sump_pump"
    },
    {
      "class_id": 4,
      "name": "fuel_tank"
    },
    {
      "class_id": 5,
      "name": "water_softener"
    },
    {
      "class_id": 6,
      "name": "breaker_box"
    },
    {
      "class_id": 7,
      "name": "fire_damage"
    },
    {
      "class_id": 8,
      "name": "washer"
    },
    {
      "class_id": 9,
      "name": "dryer"
    },
    {
      "class_id": 10,
      "name": "smoke_detector"
    },
    {
      "class_id": 11,
      "name": "furnace"
    }
  ]
}